floydpink/jsii_code_samples/__init__.py
floydpink/jsii_code_samples/py.typed
floydpink/jsii_code_samples/_jsii/__init__.py
floydpink/jsii_code_samples/_jsii/jsii-code-samples@1.0.7.jsii.tgz
floydpink.jsii_code_samples-1.0.7.dist-info/METADATA
floydpink.jsii_code_samples-1.0.7.dist-info/WHEEL
floydpink.jsii_code_samples-1.0.7.dist-info/top_level.txt
floydpink.jsii_code_samples-1.0.7.dist-info/RECORD
